geekutil/__init__.py
geekutil/math_utils.py
geekutil-0.1.0.dist-info/METADATA
geekutil-0.1.0.dist-info/WHEEL
geekutil-0.1.0.dist-info/top_level.txt
geekutil-0.1.0.dist-info/RECORD
