Metadata-Version: 2.1
Name: geekutil
Version: 0.1.0
Summary: A simple demo package for mathematical operations
Author: hskyzhou
Author-email: xezw211@126.com
